backplane/__init__.py
backplane/__main__.py
backplane/app.py
backplane/config.py
backplane/errors.py
backplane/main.py
backplane/service.py
backplane/utils.py
backplane-0.9.0.dist-info/entry_points.txt
backplane-0.9.0.dist-info/LICENSE.md
backplane-0.9.0.dist-info/WHEEL
backplane-0.9.0.dist-info/METADATA
backplane-0.9.0.dist-info/RECORD
