Metadata-Version: 2.1
Name: backplane
Version: 0.9.0
Summary: a dead-simple backplane for Dockerized applications
License: LICENSE.md
Author: Fabian Peter
Author-email: fabian@p3r.link
Requires-Python: >=3.7,<4.0
Classifier: License :: Other/Proprietary License
Classifier: Programming Language :: Python :: 3
Classifier: Programming Language :: Python :: 3.7
Classifier: Programming Language :: Python :: 3.8
Classifier: Programming Language :: Python :: 3.9
Requires-Dist: GitPython (>=3.1.11,<4.0.0)
Requires-Dist: PyYAML (>=5.3.1,<6.0.0)
Requires-Dist: anyconfig (>=0.9.11,<0.10.0)
Requires-Dist: docker (>=4.3.1,<5.0.0)
Requires-Dist: docker-compose (>=1.27.4,<2.0.0)
Requires-Dist: packaging (>=20.4,<21.0)
Requires-Dist: python-dotenv (>=0.15.0,<0.16.0)
Requires-Dist: read-version (>=0.3.1,<0.4.0)
Requires-Dist: typer[all] (>=0.3.2,<0.4.0)
Requires-Dist: validators (>=0.18.1,<0.19.0)
